vectrieve/__init__.py
vectrieve/data_loader.py
vectrieve/functions.py
vectrieve/utils.py
Vectrieve-0.1.0.dist-info/METADATA
Vectrieve-0.1.0.dist-info/WHEEL
Vectrieve-0.1.0.dist-info/top_level.txt
Vectrieve-0.1.0.dist-info/RECORD
