Metadata-Version: 2.1
Name: Vectrieve
Version: 0.1.0
Summary: Enhanced Document Semantic Search with Cosine Similarity and Document Scanning
Home-page: https://github.com/your-username/enhanced-document-search
Author: Ahsan Ali
Author-email: ahsanai440@gmail.com
Classifier: Programming Language :: Python :: 3
Classifier: License :: OSI Approved :: MIT License
Classifier: Operating System :: OS Independent
Requires-Python: >=3.10
Requires-Dist: streamlit >=1.10.0
Requires-Dist: langchain-text-splitters >=0.0.2
Requires-Dist: langchain-community >=0.0.2
Requires-Dist: numpy >=1.19.2
Requires-Dist: pandas >=1.1.3
Requires-Dist: docx2txt >=0.8
Requires-Dist: Pillow >=8.0.1
Requires-Dist: pytesseract >=0.3.8
